FIFO_Memory.v
module fifo_mem (read_out, write_in, wptr, rptr, full, wclk, w_en);

    input [7 : 0] write_in;
    input [3 : 0] wptr, rptr;
    input full, wclk, w_en;
    output [7 : 0] read_out;

    reg [8 : 0] fifo [8 : 0];


    always @(posedge wclk)
        if (w_en & !full)
            fifo [wptr[2 : 0]] <= write_in;


    assign read_out = fifo[rptr [2 : 0]] ;
endmodule

read_pointer_handler.v
module rdtr (r_binary, empty, r_gray, w_gray, en, clk, rst);



    input [3 : 0] r_gray, w_gray;
    input en, clk, rst;
    output reg [3 : 0] r_binary;
    output empty;


    always @(posedge clk or posedge rst)
        if (rst)
            r_binary <= 0;
        
        else if (en & !empty)
            r_binary <= r_binary +1;

    
    assign empty = (w_gray == r_gray);
endmodule

write_point_handler.v
module wptr (w_binary, full, w_gray, r_gray, en, clk, rst );

    //write point handler

    input [3 : 0] w_gray, r_gray;
    input en, clk, rst;
    output reg [3 : 0] w_binary;
    output full; 

    always @(posedge clk or posedge rst) begin
        if(rst)
            w_binary <= 0;

        else if (en & !full)
            w_binary <= w_binary + 1;
        
    end

    assign full = ({~w_gray[3], w_gray[2 : 0]} == r_gray);

endmodule

synchronizer.v
module synchronizer (d_out, d_in, clk, rst);

// 2 flop synchronizer

    input [3 : 0] d_in;
    reg [3 : 0] q1;
    input clk, rst;
    output reg [3 : 0] d_out;

    always @(posedge clk) begin
        
            if (rst)
                begin
                    q1 <= 0;
                    d_out <= 0;
                end
            else
                begin
                    q1 <= d_in;
                    d_out <= q1; 
                end
    end
        

endmodule

binary2gray.v
module b2g (d_out, d_in);

    input [3:0] d_in;
    output reg [3:0] d_out;
    integer i;

    always @(d_in)
        begin
            d_out[3] = d_in[3];
            for (i = 0; i<3; i= i+1)
                begin
                    d_out[i] = d_in[i] ^ d_in[i+1];
                end 
        end
endmodule

FIFO.v
module asynchronous_fifo (r_data, full, empty, w_data, r_en, w_en, w_rst, r_rst, rclk, wclk);

    input [7 : 0] w_data;
    input r_en, w_en, w_rst, r_rst, rclk, wclk;
    output [7 : 0] r_data;
    output full, empty;

    wire [3 : 0] b_wptr, b_rptr, g_wptr, g_rptr, rg_wptr, wg_rptr;

    b2g wbg(.d_out(g_wptr), .d_in(b_wptr));
    b2g rbg(.d_out(g_rptr), .d_in(b_rptr));

    synchronizer r_sync (.d_out(rg_wptr),.d_in(g_wptr), .clk(rclk), .rst(r_rst));
    synchronizer w_sync (.d_out(wg_rptr),.d_in(g_rptr), .clk(wclk), .rst(w_rst));

    wptr w1 (.w_binary(b_wptr), .full(full), .w_gray(g_wptr), .r_gray(g_rptr), .en(w_en), .clk(wclk), .rst(w_rst));
    rdtr r1 (.r_binary(b_rptr), .empty(empty), .r_gray(g_rptr), .w_gray(g_wptr), .en(r_en), .clk(rclk), .rst(r_rst));

    fifo_mem fifomem1 (.read_out(r_data), .write_in(w_data), .wptr(b_wptr), .rptr(b_rptr), .full(full), .wclk(wclk), .w_en(w_en));

endmodule

test_fifo.v
module async_fifo_tb;

    reg [7 : 0] data_in;
    reg wen, ren, wclk, rclk, wrst, rrst;

    wire [7 : 0] data_out;

    wire full, empty;
    integer i;
    
    // Inside module async_fifo_tb;
    wire [3:0] wptr_addr; // To hold the write pointer address (3 bits for index, 4 for safety)
    wire [7:0] monitored_data; // To hold the data read from the memory for monitoring

    asynchronous_fifo async_fifo (.r_data(data_out), .full(full), .empty(empty), .w_data(data_in), .r_en(ren), .w_en(wen), .w_rst(wrst), .r_rst(rrst), .rclk(rclk), .wclk(wclk));

    // Inside module async_fifo_tb, outside of initial/always blocks
    assign wptr_addr = async_fifo.fifomem1.wptr[2:0] - 1; 
    assign monitored_data = async_fifo.fifomem1.fifo[wptr_addr];

    initial begin
        rclk = 1'b0;
        wclk = 1'b0;
    end

    always #10 rclk = ~rclk;
    always #5 wclk = ~wclk;
    

    initial begin
        // Inside the initial block
        $monitor ("write data = %d, read data = %d and mem write data = %d", data_in, data_out, monitored_data);
        $dumpfile("async_fifo.vcd");
        $dumpvars(0,async_fifo_tb);

        for (i = 0; i<200 ; i = i + 1)
            begin
                if (full) begin
                    wen = 0;
                    #10;
                end
                else begin
                    #10 wen = 1; data_in = i;
                end
            end
        #10 $finish;
    end

    initial begin
        wen = 1'b0;
        ren = 1'b0;
        #10 wen = 1'b1;
        ren = 1'b1;
    end

    initial begin
        wrst = 1; rrst = 1;
        #10 wrst = 0; rrst = 0;
    end
endmodule

async_fifo.vcd
$date
	Mon Oct 27 20:53:29 2025
$end
$version
	Icarus Verilog
$end
$timescale
	1s
$end
$scope module async_fifo_tb $end
$var wire 4 ! wptr_addr [3:0] $end
$var wire 8 " monitored_data [7:0] $end
$var wire 1 # full $end
$var wire 1 $ empty $end
$var wire 8 % data_out [7:0] $end
$var reg 8 & data_in [7:0] $end
$var reg 1 ' rclk $end
$var reg 1 ( ren $end
$var reg 1 ) rrst $end
$var reg 1 * wclk $end
$var reg 1 + wen $end
$var reg 1 , wrst $end
$var integer 32 - i [31:0] $end
$scope module async_fifo $end
$var wire 1 ( r_en $end
$var wire 1 ) r_rst $end
$var wire 1 ' rclk $end
$var wire 8 . w_data [7:0] $end
$var wire 1 + w_en $end
$var wire 1 , w_rst $end
$var wire 1 * wclk $end
$var wire 4 / wg_rptr [3:0] $end
$var wire 4 0 rg_wptr [3:0] $end
$var wire 8 1 r_data [7:0] $end
$var wire 4 2 g_wptr [3:0] $end
$var wire 4 3 g_rptr [3:0] $end
$var wire 1 # full $end
$var wire 1 $ empty $end
$var wire 4 4 b_wptr [3:0] $end
$var wire 4 5 b_rptr [3:0] $end
$scope module fifomem1 $end
$var wire 1 + w_en $end
$var wire 1 * wclk $end
$var wire 8 6 write_in [7:0] $end
$var wire 4 7 wptr [3:0] $end
$var wire 4 8 rptr [3:0] $end
$var wire 8 9 read_out [7:0] $end
$var wire 1 # full $end
$upscope $end
$scope module r1 $end
$var wire 1 ' clk $end
$var wire 1 ( en $end
$var wire 1 ) rst $end
$var wire 4 : w_gray [3:0] $end
$var wire 4 ; r_gray [3:0] $end
$var wire 1 $ empty $end
$var reg 4 < r_binary [3:0] $end
$upscope $end
$scope module r_sync $end
$var wire 1 ' clk $end
$var wire 1 ) rst $end
$var wire 4 = d_in [3:0] $end
$var reg 4 > d_out [3:0] $end
$var reg 4 ? q1 [3:0] $end
$upscope $end
$scope module rbg $end
$var wire 4 @ d_in [3:0] $end
$var reg 4 A d_out [3:0] $end
$var integer 32 B i [31:0] $end
$upscope $end
$scope module w1 $end
$var wire 1 * clk $end
$var wire 1 + en $end
$var wire 4 C r_gray [3:0] $end
$var wire 1 , rst $end
$var wire 4 D w_gray [3:0] $end
$var wire 1 # full $end
$var reg 4 E w_binary [3:0] $end
$upscope $end
$scope module w_sync $end
$var wire 1 * clk $end
$var wire 4 F d_in [3:0] $end
$var wire 1 , rst $end
$var reg 4 G d_out [3:0] $end
$var reg 4 H q1 [3:0] $end
$upscope $end
$scope module wbg $end
$var wire 4 I d_in [3:0] $end
$var reg 4 J d_out [3:0] $end
$var integer 32 K i [31:0] $end
$upscope $end
$upscope $end
$upscope $end
$enddefinitions $end
$comment Show the parameter values. $end
$dumpall
$end
#0
$dumpvars
b11 K
b0 J
b0 I
bx H
bx G
b0 F
b0 E
b0 D
b0 C
b11 B
b0 A
b0 @
bx ?
bx >
b0 =
b0 <
b0 ;
b0 :
bx 9
b0 8
b0 7
bx 6
b0 5
b0 4
b0 3
b0 2
bx 1
bx 0
bx /
bx .
b0 -
1,
0+
0*
1)
0(
0'
bx &
bx %
1$
0#
bx "
b1111 !
$end
#5
b0 /
b0 G
b0 H
1*
#10
b0 ?
0*
0)
0,
1(
b1 -
b0 &
b0 .
b0 6
1+
1'
#15
b0 "
b0 %
b0 1
b0 9
b0 !
0$
b1 2
b1 :
b1 =
b1 D
b1 J
b11 K
b1 4
b1 7
b1 E
b1 I
1*
#20
0*
b10 -
b1 &
b1 .
b1 6
0'
#25
b1 "
b1 !
b11 2
b11 :
b11 =
b11 D
b11 J
b11 K
b10 4
b10 7
b10 E
b10 I
1*
#30
b1 %
b1 1
b1 9
b1 3
b1 ;
b1 A
b1 C
b1 F
b11 B
b1 5
b1 8
b1 <
b1 @
b0 0
b0 >
b11 ?
0*
b11 -
b10 &
b10 .
b10 6
1'
#35
b10 "
b10 !
b10 2
b10 :
b10 =
b10 D
b10 J
b11 K
b1 H
b11 4
b11 7
b11 E
b11 I
1*
#40
0*
b100 -
b11 &
b11 .
b11 6
0'
#45
b11 "
b11 !
b110 2
b110 :
b110 =
b110 D
b110 J
b11 K
b1 /
b1 G
b100 4
b100 7
b100 E
b100 I
1*
#50
b10 %
b10 1
b10 9
b11 3
b11 ;
b11 A
b11 C
b11 F
b11 B
b10 5
b10 8
b10 <
b10 @
b11 0
b11 >
b110 ?
0*
b101 -
b100 &
b100 .
b100 6
1'
#55
b100 "
b100 !
b111 2
b111 :
b111 =
b111 D
b111 J
b11 K
b11 H
b101 4
b101 7
b101 E
b101 I
1*
#60
0*
b110 -
b101 &
b101 .
b101 6
0'
#65
b101 "
b101 !
b101 2
b101 :
b101 =
b101 D
b101 J
b11 K
b11 /
b11 G
b110 4
b110 7
b110 E
b110 I
1*
#70
b11 %
b11 1
b11 9
b10 3
b10 ;
b10 A
b10 C
b10 F
b11 B
b11 5
b11 8
b11 <
b11 @
b110 0
b110 >
b101 ?
0*
b111 -
b110 &
b110 .
b110 6
1'
#75
b110 "
b110 !
b100 2
b100 :
b100 =
b100 D
b100 J
b11 K
b10 H
b111 4
b111 7
b111 E
b111 I
1*
#80
0*
b1000 -
b111 &
b111 .
b111 6
0'
#85
bx "
b1111 !
b11 K
b1100 2
b1100 :
b1100 =
b1100 D
b1100 J
b10 /
b10 G
b1000 4
b1000 7
b1000 E
b1000 I
1*
#90
b100 %
b100 1
b100 9
b110 3
b110 ;
b110 A
b110 C
b110 F
b11 B
b100 5
b100 8
b100 <
b100 @
b101 0
b101 >
b1100 ?
0*
b1001 -
b1000 &
b1000 .
b1000 6
1'
#95
b1000 "
b0 !
b1101 2
b1101 :
b1101 =
b1101 D
b1101 J
b11 K
b110 H
b1001 4
b1001 7
b1001 E
b1001 I
1*
#100
0*
b1010 -
b1001 &
b1001 .
b1001 6
0'
#105
b1001 "
b1 !
b1111 2
b1111 :
b1111 =
b1111 D
b1111 J
b11 K
b110 /
b110 G
b1010 4
b1010 7
b1010 E
b1010 I
1*
#110
b101 %
b101 1
b101 9
1#
b111 3
b111 ;
b111 A
b111 C
b111 F
b11 B
b101 5
b101 8
b101 <
b101 @
b1100 0
b1100 >
b1111 ?
0*
b1011 -
b1010 &
b1010 .
b1010 6
1'
#115
b111 H
1*
#120
0*
0+
b1100 -
b1011 &
b1011 .
b1011 6
0'
#125
b111 /
b111 G
1*
#130
b110 %
b110 1
b110 9
0#
b101 3
b101 ;
b101 A
b101 C
b101 F
b11 B
b110 5
b110 8
b110 <
b110 @
b1111 0
b1111 >
0*
b1101 -
1'
#135
b101 H
1*
#140
0*
b1110 -
0'
#145
b101 /
b101 G
1*
#150
b111 %
b111 1
b111 9
b100 3
b100 ;
b100 A
b100 C
b100 F
b11 B
b111 5
b111 8
b111 <
b111 @
0*
b1111 -
b1110 &
b1110 .
b1110 6
1+
1'
#155
b1110 "
b10 !
b1110 2
b1110 :
b1110 =
b1110 D
b1110 J
b11 K
b100 H
b1011 4
b1011 7
b1011 E
b1011 I
1*
#160
0*
b10000 -
b1111 &
b1111 .
b1111 6
0'
#165
b1111 "
b11 !
b1010 2
b1010 :
b1010 =
b1010 D
b1010 J
b11 K
b100 /
b100 G
b1100 4
b1100 7
b1100 E
b1100 I
1*
#170
b1000 %
b1000 1
b1000 9
b11 B
b1100 3
b1100 ;
b1100 A
b1100 C
b1100 F
b1000 5
b1000 8
b1000 <
b1000 @
b1010 ?
0*
b10001 -
b10000 &
b10000 .
b10000 6
1'
#175
b10000 "
b100 !
b1011 2
b1011 :
b1011 =
b1011 D
b1011 J
b11 K
b1100 H
b1101 4
b1101 7
b1101 E
b1101 I
1*
#180
0*
b10010 -
b10001 &
b10001 .
b10001 6
0'
#185
b10001 "
b101 !
b1001 2
b1001 :
b1001 =
b1001 D
b1001 J
b11 K
b1100 /
b1100 G
b1110 4
b1110 7
b1110 E
b1110 I
1*
#190
b1001 %
b1001 1
b1001 9
b1101 3
b1101 ;
b1101 A
b1101 C
b1101 F
b11 B
b1001 5
b1001 8
b1001 <
b1001 @
b1010 0
b1010 >
b1001 ?
0*
b10011 -
b10010 &
b10010 .
b10010 6
1'
#195
b10010 "
b110 !
b1000 2
b1000 :
b1000 =
b1000 D
b1000 J
b11 K
b1101 H
b1111 4
b1111 7
b1111 E
b1111 I
1*
#200
0*
b10100 -
b10011 &
b10011 .
b10011 6
0'
#205
bx "
b1111 !
b11 K
b0 2
b0 :
b0 =
b0 D
b0 J
b1101 /
b1101 G
b0 4
b0 7
b0 E
b0 I
1*
#210
b1110 %
b1110 1
b1110 9
b1111 3
b1111 ;
b1111 A
b1111 C
b1111 F
b11 B
b1010 5
b1010 8
b1010 <
b1010 @
b1001 0
b1001 >
b0 ?
0*
b10101 -
b10100 &
b10100 .
b10100 6
1'
#215
b10100 "
b0 !
b1 2
b1 :
b1 =
b1 D
b1 J
b11 K
b1111 H
b1 4
b1 7
b1 E
b1 I
1*
#220
0*
b10110 -
b10101 &
b10101 .
b10101 6
0'
#225
b10101 "
b1 !
b11 2
b11 :
b11 =
b11 D
b11 J
b11 K
b1111 /
b1111 G
b10 4
b10 7
b10 E
b10 I
1*
#230
b1111 %
b1111 1
b1111 9
b1110 3
b1110 ;
b1110 A
b1110 C
b1110 F
b11 B
b1011 5
b1011 8
b1011 <
b1011 @
b0 0
b0 >
b11 ?
0*
b10111 -
b10110 &
b10110 .
b10110 6
1'
#235
b10110 "
b10 !
b10 2
b10 :
b10 =
b10 D
b10 J
b11 K
b1110 H
b11 4
b11 7
b11 E
b11 I
1*
#240
0*
b11000 -
b10111 &
b10111 .
b10111 6
0'
#245
b10111 "
1#
b10111 %
b10111 1
b10111 9
b11 !
b110 2
b110 :
b110 =
b110 D
b110 J
b11 K
b1110 /
b1110 G
b100 4
b100 7
b100 E
b100 I
1*
#250
b10000 %
b10000 1
b10000 9
0#
b1010 3
b1010 ;
b1010 A
b1010 C
b1010 F
b11 B
b1100 5
b1100 8
b1100 <
b1100 @
b11 0
b11 >
b110 ?
0*
0+
b11001 -
b11000 &
b11000 .
b11000 6
1'
#255
b1010 H
1*
#260
0*
b11010 -
0'
#265
b1010 /
b1010 G
1*
#270
b10001 %
b10001 1
b10001 9
b1011 3
b1011 ;
b1011 A
b1011 C
b1011 F
b11 B
b1101 5
b1101 8
b1101 <
b1101 @
b110 0
b110 >
0*
b11011 -
b11010 &
b11010 .
b11010 6
1+
1'
#275
b11010 "
b100 !
b111 2
b111 :
b111 =
b111 D
b111 J
b11 K
b1011 H
b101 4
b101 7
b101 E
b101 I
1*
#280
0*
b11100 -
b11011 &
b11011 .
b11011 6
0'
#285
b11011 "
b11011 %
b11011 1
b11011 9
b101 !
b101 2
b101 :
b101 =
b101 D
b101 J
b11 K
b1011 /
b1011 G
b110 4
b110 7
b110 E
b110 I
1*
#290
b10010 %
b10010 1
b10010 9
b1001 3
b1001 ;
b1001 A
b1001 C
b1001 F
b11 B
b1110 5
b1110 8
b1110 <
b1110 @
b101 ?
0*
b11101 -
b11100 &
b11100 .
b11100 6
1'
#295
b11100 "
b11100 %
b11100 1
b11100 9
b110 !
b100 2
b100 :
b100 =
b100 D
b100 J
b11 K
b1001 H
b111 4
b111 7
b111 E
b111 I
1*
#300
0*
b11110 -
b11101 &
b11101 .
b11101 6
0'
#305
bx "
b1111 !
b11 K
b1100 2
b1100 :
b1100 =
b1100 D
b1100 J
b1001 /
b1001 G
b1000 4
b1000 7
b1000 E
b1000 I
1*
#310
b11101 %
b11101 1
b11101 9
b1000 3
b1000 ;
b1000 A
b1000 C
b1000 F
b11 B
b1111 5
b1111 8
b1111 <
b1111 @
b101 0
b101 >
b1100 ?
0*
b11111 -
b11110 &
b11110 .
b11110 6
1'
#315
b11110 "
b0 !
b1101 2
b1101 :
b1101 =
b1101 D
b1101 J
b11 K
b1000 H
b1001 4
b1001 7
b1001 E
b1001 I
1*
#320
0*
b100000 -
b11111 &
b11111 .
b11111 6
0'
#325
b11111 "
b1 !
b1111 2
b1111 :
b1111 =
b1111 D
b1111 J
b11 K
b1000 /
b1000 G
b1010 4
b1010 7
b1010 E
b1010 I
1*
#330
b11110 %
b11110 1
b11110 9
b11 B
b0 3
b0 ;
b0 A
b0 C
b0 F
b0 5
b0 8
b0 <
b0 @
b1100 0
b1100 >
b1111 ?
0*
b100001 -
b100000 &
b100000 .
b100000 6
1'
#335
b100000 "
b10 !
b1110 2
b1110 :
b1110 =
b1110 D
b1110 J
b11 K
b0 H
b1011 4
b1011 7
b1011 E
b1011 I
1*
#340
0*
b100010 -
b100001 &
b100001 .
b100001 6
0'
#345
b100001 "
b11 !
b1010 2
b1010 :
b1010 =
b1010 D
b1010 J
b11 K
b0 /
b0 G
b1100 4
b1100 7
b1100 E
b1100 I
1*
#350
b11111 %
b11111 1
b11111 9
b1 3
b1 ;
b1 A
b1 C
b1 F
b11 B
b1 5
b1 8
b1 <
b1 @
b1111 0
b1111 >
b1010 ?
0*
b100011 -
b100010 &
b100010 .
b100010 6
1'
#355
b100010 "
b100 !
b1011 2
b1011 :
b1011 =
b1011 D
b1011 J
b11 K
b1 H
b1101 4
b1101 7
b1101 E
b1101 I
1*
#360
0*
b100100 -
b100011 &
b100011 .
b100011 6
0'
#365
b100011 "
1#
b101 !
b1001 2
b1001 :
b1001 =
b1001 D
b1001 J
b11 K
b1 /
b1 G
b1110 4
b1110 7
b1110 E
b1110 I
1*
#370
b100000 %
b100000 1
b100000 9
0#
b11 3
b11 ;
b11 A
b11 C
b11 F
b11 B
b10 5
b10 8
b10 <
b10 @
b1010 0
b1010 >
b1001 ?
0*
0+
b100101 -
b100100 &
b100100 .
b100100 6
1'
#375
b11 H
1*
#380
0*
b100110 -
0'
#385
b11 /
b11 G
1*
#390
b100001 %
b100001 1
b100001 9
b10 3
b10 ;
b10 A
b10 C
b10 F
b11 B
b11 5
b11 8
b11 <
b11 @
b1001 0
b1001 >
0*
b100111 -
b100110 &
b100110 .
b100110 6
1+
1'
#395
b100110 "
b110 !
b1000 2
b1000 :
b1000 =
b1000 D
b1000 J
b11 K
b10 H
b1111 4
b1111 7
b1111 E
b1111 I
1*
#400
0*
b101000 -
b100111 &
b100111 .
b100111 6
0'
#405
bx "
b1111 !
b11 K
b0 2
b0 :
b0 =
b0 D
b0 J
b10 /
b10 G
b0 4
b0 7
b0 E
b0 I
1*
#410
b100010 %
b100010 1
b100010 9
b110 3
b110 ;
b110 A
b110 C
b110 F
b11 B
b100 5
b100 8
b100 <
b100 @
b0 ?
0*
b101001 -
b101000 &
b101000 .
b101000 6
1'
#415
b101000 "
b0 !
b1 2
b1 :
b1 =
b1 D
b1 J
b11 K
b110 H
b1 4
b1 7
b1 E
b1 I
1*
#420
0*
b101010 -
b101001 &
b101001 .
b101001 6
0'
#425
b101001 "
b1 !
b11 2
b11 :
b11 =
b11 D
b11 J
b11 K
b110 /
b110 G
b10 4
b10 7
b10 E
b10 I
1*
#430
b100011 %
b100011 1
b100011 9
b111 3
b111 ;
b111 A
b111 C
b111 F
b11 B
b101 5
b101 8
b101 <
b101 @
b0 0
b0 >
b11 ?
0*
b101011 -
b101010 &
b101010 .
b101010 6
1'
#435
b101010 "
b10 !
b10 2
b10 :
b10 =
b10 D
b10 J
b11 K
b111 H
b11 4
b11 7
b11 E
b11 I
1*
#440
0*
b101100 -
b101011 &
b101011 .
b101011 6
0'
#445
b101011 "
b11 !
b110 2
b110 :
b110 =
b110 D
b110 J
b11 K
b111 /
b111 G
b100 4
b100 7
b100 E
b100 I
1*
#450
b100110 %
b100110 1
b100110 9
b101 3
b101 ;
b101 A
b101 C
b101 F
b11 B
b110 5
b110 8
b110 <
b110 @
b11 0
b11 >
b110 ?
0*
b101101 -
b101100 &
b101100 .
b101100 6
1'
#455
b101100 "
b100 !
b111 2
b111 :
b111 =
b111 D
b111 J
b11 K
b101 H
b101 4
b101 7
b101 E
b101 I
1*
#460
0*
b101110 -
b101101 &
b101101 .
b101101 6
0'
#465
b101101 "
b101 !
1$
b101 2
b101 :
b101 =
b101 D
b101 J
b11 K
b101 /
b101 G
b110 4
b110 7
b110 E
b110 I
1*
#470
b110 0
b110 >
b101 ?
0*
b101111 -
b101110 &
b101110 .
b101110 6
1'
#475
b101110 "
b101110 %
b101110 1
b101110 9
b110 !
0$
b100 2
b100 :
b100 =
b100 D
b100 J
b11 K
b111 4
b111 7
b111 E
b111 I
1*
#480
0*
b110000 -
b101111 &
b101111 .
b101111 6
0'
#485
bx "
b1111 !
b11 K
b1100 2
b1100 :
b1100 =
b1100 D
b1100 J
b1000 4
b1000 7
b1000 E
b1000 I
1*
#490
b101111 %
b101111 1
b101111 9
1#
b100 3
b100 ;
b100 A
b100 C
b100 F
b11 B
b111 5
b111 8
b111 <
b111 @
b101 0
b101 >
b1100 ?
0*
b110001 -
b110000 &
b110000 .
b110000 6
1'
#495
b100 H
1*
#500
0*
0+
b110010 -
b110001 &
b110001 .
b110001 6
0'
#505
b100 /
b100 G
1*
#510
b101000 %
b101000 1
b101000 9
b11 B
0#
1$
b1100 3
b1100 ;
b1100 A
b1100 C
b1100 F
b1000 5
b1000 8
b1000 <
b1000 @
b1100 0
b1100 >
0*
b110011 -
1'
#515
b1100 H
1*
#520
0*
b110100 -
0'
#525
b1100 /
b1100 G
1*
#530
0*
b110101 -
b110100 &
b110100 .
b110100 6
1+
1'
#535
b110100 "
b110100 %
b110100 1
b110100 9
b0 !
0$
b1101 2
b1101 :
b1101 =
b1101 D
b1101 J
b11 K
b1001 4
b1001 7
b1001 E
b1001 I
1*
#540
0*
b110110 -
b110101 &
b110101 .
b110101 6
0'
#545
b110101 "
b1 !
b1111 2
b1111 :
b1111 =
b1111 D
b1111 J
b11 K
b1010 4
b1010 7
b1010 E
b1010 I
1*
#550
b110101 %
b110101 1
b110101 9
b1101 3
b1101 ;
b1101 A
b1101 C
b1101 F
b11 B
b1001 5
b1001 8
b1001 <
b1001 @
b1111 ?
0*
b110111 -
b110110 &
b110110 .
b110110 6
1'
#555
b110110 "
b10 !
b1110 2
b1110 :
b1110 =
b1110 D
b1110 J
b11 K
b1101 H
b1011 4
b1011 7
b1011 E
b1011 I
1*
#560
0*
b111000 -
b110111 &
b110111 .
b110111 6
0'
#565
b110111 "
b11 !
b1010 2
b1010 :
b1010 =
b1010 D
b1010 J
b11 K
b1101 /
b1101 G
b1100 4
b1100 7
b1100 E
b1100 I
1*
#570
b110110 %
b110110 1
b110110 9
b1111 3
b1111 ;
b1111 A
b1111 C
b1111 F
b11 B
b1010 5
b1010 8
b1010 <
b1010 @
b1111 0
b1111 >
b1010 ?
0*
b111001 -
b111000 &
b111000 .
b111000 6
1'
#575
b111000 "
b100 !
b1011 2
b1011 :
b1011 =
b1011 D
b1011 J
b11 K
b1111 H
b1101 4
b1101 7
b1101 E
b1101 I
1*
#580
0*
b111010 -
b111001 &
b111001 .
b111001 6
0'
#585
b111001 "
b101 !
b1001 2
b1001 :
b1001 =
b1001 D
b1001 J
b11 K
b1111 /
b1111 G
b1110 4
b1110 7
b1110 E
b1110 I
1*
#590
b110111 %
b110111 1
b110111 9
b1110 3
b1110 ;
b1110 A
b1110 C
b1110 F
b11 B
b1011 5
b1011 8
b1011 <
b1011 @
b1010 0
b1010 >
b1001 ?
0*
b111011 -
b111010 &
b111010 .
b111010 6
1'
#595
b111010 "
b110 !
b1000 2
b1000 :
b1000 =
b1000 D
b1000 J
b11 K
b1110 H
b1111 4
b1111 7
b1111 E
b1111 I
1*
#600
0*
b111100 -
b111011 &
b111011 .
b111011 6
0'
#605
bx "
b1111 !
b11 K
b0 2
b0 :
b0 =
b0 D
b0 J
b1110 /
b1110 G
b0 4
b0 7
b0 E
b0 I
1*
#610
b111000 %
b111000 1
b111000 9
b1010 3
b1010 ;
b1010 A
b1010 C
b1010 F
b11 B
b1100 5
b1100 8
b1100 <
b1100 @
b1001 0
b1001 >
b0 ?
0*
b111101 -
b111100 &
b111100 .
b111100 6
1'
#615
b111100 "
b0 !
b1 2
b1 :
b1 =
b1 D
b1 J
b11 K
b1010 H
b1 4
b1 7
b1 E
b1 I
1*
#620
0*
b111110 -
b111101 &
b111101 .
b111101 6
0'
#625
b111101 "
b1 !
b11 2
b11 :
b11 =
b11 D
b11 J
b11 K
b1010 /
b1010 G
b10 4
b10 7
b10 E
b10 I
1*
#630
b111001 %
b111001 1
b111001 9
1#
b1011 3
b1011 ;
b1011 A
b1011 C
b1011 F
b11 B
b1101 5
b1101 8
b1101 <
b1101 @
b0 0
b0 >
b11 ?
0*
b111111 -
b111110 &
b111110 .
b111110 6
1'
#635
b1011 H
1*
#640
0*
0+
b1000000 -
b111111 &
b111111 .
b111111 6
0'
#645
b1011 /
b1011 G
1*
#650
b111010 %
b111010 1
b111010 9
0#
b1001 3
b1001 ;
b1001 A
b1001 C
b1001 F
b11 B
b1110 5
b1110 8
b1110 <
b1110 @
b11 0
b11 >
0*
b1000001 -
1'
#655
b1001 H
1*
#660
0*
b1000010 -
0'
#665
b1001 /
b1001 G
1*
#670
b111011 %
b111011 1
b111011 9
b1000 3
b1000 ;
b1000 A
b1000 C
b1000 F
b11 B
b1111 5
b1111 8
b1111 <
b1111 @
0*
b1000011 -
b1000010 &
b1000010 .
b1000010 6
1+
1'
#675
b1000010 "
b10 !
b10 2
b10 :
b10 =
b10 D
b10 J
b11 K
b1000 H
b11 4
b11 7
b11 E
b11 I
1*
#680
0*
b1000100 -
b1000011 &
b1000011 .
b1000011 6
0'
#685
b1000011 "
b11 !
b110 2
b110 :
b110 =
b110 D
b110 J
b11 K
b1000 /
b1000 G
b100 4
b100 7
b100 E
b100 I
1*
#690
b111100 %
b111100 1
b111100 9
b11 B
b0 3
b0 ;
b0 A
b0 C
b0 F
b0 5
b0 8
b0 <
b0 @
b110 ?
0*
b1000101 -
b1000100 &
b1000100 .
b1000100 6
1'
#695
b1000100 "
b100 !
b111 2
b111 :
b111 =
b111 D
b111 J
b11 K
b0 H
b101 4
b101 7
b101 E
b101 I
1*
#700
0*
b1000110 -
b1000101 &
b1000101 .
b1000101 6
0'
#705
b1000101 "
b101 !
b101 2
b101 :
b101 =
b101 D
b101 J
b11 K
b0 /
b0 G
b110 4
b110 7
b110 E
b110 I
1*
#710
b111101 %
b111101 1
b111101 9
b1 3
b1 ;
b1 A
b1 C
b1 F
b11 B
b1 5
b1 8
b1 <
b1 @
b110 0
b110 >
b101 ?
0*
b1000111 -
b1000110 &
b1000110 .
b1000110 6
1'
#715
b1000110 "
b110 !
b100 2
b100 :
b100 =
b100 D
b100 J
b11 K
b1 H
b111 4
b111 7
b111 E
b111 I
1*
#720
0*
b1001000 -
b1000111 &
b1000111 .
b1000111 6
0'
#725
bx "
b1111 !
b11 K
b1100 2
b1100 :
b1100 =
b1100 D
b1100 J
b1 /
b1 G
b1000 4
b1000 7
b1000 E
b1000 I
1*
#730
b1000010 %
b1000010 1
b1000010 9
b11 3
b11 ;
b11 A
b11 C
b11 F
b11 B
b10 5
b10 8
b10 <
b10 @
b101 0
b101 >
b1100 ?
0*
b1001001 -
b1001000 &
b1001000 .
b1001000 6
1'
#735
b1001000 "
b0 !
b1101 2
b1101 :
b1101 =
b1101 D
b1101 J
b11 K
b11 H
b1001 4
b1001 7
b1001 E
b1001 I
1*
#740
0*
b1001010 -
b1001001 &
b1001001 .
b1001001 6
0'
#745
b1001001 "
b1 !
b1111 2
b1111 :
b1111 =
b1111 D
b1111 J
b11 K
b11 /
b11 G
b1010 4
b1010 7
b1010 E
b1010 I
1*
#750
b1000011 %
b1000011 1
b1000011 9
b10 3
b10 ;
b10 A
b10 C
b10 F
b11 B
b11 5
b11 8
b11 <
b11 @
b1100 0
b1100 >
b1111 ?
0*
b1001011 -
b1001010 &
b1001010 .
b1001010 6
1'
#755
b1001010 "
b10 !
b1110 2
b1110 :
b1110 =
b1110 D
b1110 J
b11 K
b10 H
b1011 4
b1011 7
b1011 E
b1011 I
1*
#760
0*
b1001100 -
b1001011 &
b1001011 .
b1001011 6
0'
#765
b1001011 "
1#
b1001011 %
b1001011 1
b1001011 9
b11 !
b1010 2
b1010 :
b1010 =
b1010 D
b1010 J
b11 K
b10 /
b10 G
b1100 4
b1100 7
b1100 E
b1100 I
1*
#770
b1000100 %
b1000100 1
b1000100 9
0#
b110 3
b110 ;
b110 A
b110 C
b110 F
b11 B
b100 5
b100 8
b100 <
b100 @
b1111 0
b1111 >
b1010 ?
0*
0+
b1001101 -
b1001100 &
b1001100 .
b1001100 6
1'
#775
b110 H
1*
#780
0*
b1001110 -
0'
#785
b110 /
b110 G
1*
#790
b1000101 %
b1000101 1
b1000101 9
b111 3
b111 ;
b111 A
b111 C
b111 F
b11 B
b101 5
b101 8
b101 <
b101 @
b1010 0
b1010 >
0*
b1001111 -
b1001110 &
b1001110 .
b1001110 6
1+
1'
#795
b1001110 "
b100 !
b1011 2
b1011 :
b1011 =
b1011 D
b1011 J
b11 K
b111 H
b1101 4
b1101 7
b1101 E
b1101 I
1*
#800
0*
b1010000 -
b1001111 &
b1001111 .
b1001111 6
0'
#805
b1001111 "
b1001111 %
b1001111 1
b1001111 9
b101 !
b1001 2
b1001 :
b1001 =
b1001 D
b1001 J
b11 K
b111 /
b111 G
b1110 4
b1110 7
b1110 E
b1110 I
1*
