synchronizer.v
module synchronizer (d_out, d_in, clk, rst);

// 2 flop synchronizer

    input [3 : 0] d_in;
    reg [3 : 0] q1;
    input clk, rst;
    output reg [3 : 0] d_out;

    always @(posedge clk) begin
        
            if (rst)
                begin
                    q1 <= 0;
                    d_out <= 0;
                end
            else
                begin
                    q1 <= d_in;
                    d_out <= q1; 
                end
    end
        

endmodule

test_synchronizer.v
module test;

    reg [3 : 0] d_in;
    wire [3 : 0] d_out;
    reg clk, rst;

    synchronizer sync(d_out,d_in,clk,rst);

    initial clk = 1'b0;
    always #5 clk = ~clk;

    initial begin
        rst = 1'b1; d_in = 4'b0000;
        #10 rst = 1'b0;
        #10 d_in = 4'b0001;
        #10 d_in = 4'b0010;
        #10 d_in = 4'b0101;
        #10 d_in = 4'b1111;
    end

    initial begin
        $monitor("time = %t  :: input = %d, intermediate = %d, output = %d",$time, d_in, sync.q1, d_out);
        $dumpfile("sync.vcd");
        $dumpvars(0,test);
        #70 $finish;
    end
endmodule

sync.vcd
$date
	Mon Oct 27 19:18:38 2025
$end
$version
	Icarus Verilog
$end
$timescale
	1s
$end
$scope module test $end
$var wire 4 ! d_out [3:0] $end
$var reg 1 " clk $end
$var reg 4 # d_in [3:0] $end
$var reg 1 $ rst $end
$scope module sync $end
$var wire 1 " clk $end
$var wire 4 % d_in [3:0] $end
$var wire 1 $ rst $end
$var reg 4 & d_out [3:0] $end
$var reg 4 ' q1 [3:0] $end
$upscope $end
$upscope $end
$enddefinitions $end
$comment Show the parameter values. $end
$dumpall
$end
#0
$dumpvars
bx '
bx &
b0 %
1$
b0 #
0"
bx !
$end
#5
b0 !
b0 &
b0 '
1"
#10
0"
0$
#15
1"
#20
0"
b1 #
b1 %
#25
b1 '
1"
#30
0"
b10 #
b10 %
#35
b1 !
b1 &
b10 '
1"
#40
0"
b101 #
b101 %
#45
b10 !
b10 &
b101 '
1"
#50
0"
b1111 #
b1111 %
#55
b101 !
b101 &
b1111 '
1"
#60
0"
#65
b1111 !
b1111 &
1"
